neurodatagen/__init__.py
neurodatagen/eeg/__init__.py
neurodatagen/eeg/gen_eeg.py
neurodatagen/eeg/gen_eeg_mne.py
neurodatagen/ephys/__init__.py
neurodatagen/ephys/gen_ephys.py
neurodatagen/ephys/gen_spiketimes.py
neurodatagen/ephys/gen_waveforms.py
neurodatagen/ephys/load_waveforms.py
neurodatagen/imaging/__init__.py
neurodatagen/imaging/gen_miniscope.py
neurodatagen-0.1.0a4.dist-info/LICENSE.txt
neurodatagen-0.1.0a4.dist-info/METADATA
neurodatagen-0.1.0a4.dist-info/WHEEL
neurodatagen-0.1.0a4.dist-info/top_level.txt
neurodatagen-0.1.0a4.dist-info/RECORD
