Metadata-Version: 2.1
Name: neurodatagen
Version: 0.1.0a4
Summary: Neuroscience data generation
Author-email: Demetris Roumis <8qdo8efl3@mozmail.com>
Requires-Python: >=3.8
License-File: LICENSE.txt
Requires-Dist: numpy
Requires-Dist: mne
Requires-Dist: neurodsp
Requires-Dist: pandas
Requires-Dist: dask
Requires-Dist: sparse
Requires-Dist: xarray
Requires-Dist: scipy
